{
  "features": [
    "WAI ARIA Separator pattern implementation",
    "Keyboard navigation with arrow keys and Home/End",
    "Collapsible panels with custom thresholds",
    "Responsive resizing with min/max constraints",
    "Panel size synchronization across handles",
    "Dynamic orientation (horizontal/vertical)",
    "Fine-grained resizing control with Shift key",
    "Progressive size adjustments with step values",
    "Custom collapse/expand behaviors with callbacks",
    "Flexible initial sizing with auto-distribution",
    "Accessible resize handles with ARIA attributes"
  ],
  "keyboard": {
    "shortcuts": [
      {
        "key": "ArrowLeft",
        "comment": "When focus is on the handle and orientation is horizontal, decreases size of previous panel by 1%"
      },
      {
        "key": "ArrowRight",
        "comment": "When focus is on the handle and orientation is horizontal, increases size of previous panel by 1%"
      },
      {
        "key": "ArrowUp",
        "comment": "When focus is on the handle and orientation is vertical, decreases size of previous panel by 1%"
      },
      {
        "key": "ArrowDown",
        "comment": "When focus is on the handle and orientation is vertical, increases size of previous panel by 1%"
      },
      {
        "key": "Shift + Arrow keys",
        "comment": "When focus is on the handle, adjusts panel size by 10% instead of 1%"
      },
      {
        "key": "Home",
        "comment": "When focus is on the handle, collapses previous panel to its minimum size"
      },
      {
        "key": "End",
        "comment": "When focus is on the handle, expands previous panel to its maximum size"
      }
    ]
  }
}
